Metadata-Version: 2.1
Name: jsonforms
Version: 1.0
Summary: Json object validation check.
Author-email: dimabykov189@gmail.com
